[
    {
        "Style":"Abstract-Expressionism",
        "Artwork":"Faciamus hominem (Genesis 1:26)",
        "Artist":"Salvador Dali",
        "Date":"1964",
        "Link":"https:\/\/uploads0.wikiart.org\/images\/salvador-dali\/faciamus-hominem-genesis-1-26-1964.jpg",
        "hash":"c3ce92a14908d7ba43e8f115e9fecf1e",
        "category":"paint",
        "caption":"Faciamus hominem (Genesis 1:26) by Salvador Dali, Abstract-Expressionism (1964)"
    },
    {
        "Style":"Abstract-Expressionism",
        "Artwork":"Portrait of St. Jerome",
        "Artist":"Salvador Dali",
        "Date":"1960",
        "Link":"https:\/\/uploads5.wikiart.org\/images\/salvador-dali\/portrait-of-st-jerome.jpg",
        "hash":"d03c4e8af26769de1fcaa9b8d1991893",
        "category":"other",
        "caption":"Portrait of St. Jerome by Salvador Dali, Abstract-Expressionism (1960)"
    },
    {
        "Style":"Abstract-Expressionism",
        "Artwork":"Abraham, pater multarem gentium (Genesis 12:1f)",
        "Artist":"Salvador Dali",
        "Date":"1964-1967",
        "Link":"https:\/\/uploads6.wikiart.org\/images\/salvador-dali\/abraham-pater-multarem-gentium-genesis-12-1f-1967.jpg",
        "hash":"123c7a4a8a13d1c1912014d00b4d9123",
        "category":"paint",
        "caption":"Abraham, pater multarem gentium (Genesis 12:1f) by Salvador Dali, Abstract-Expressionism (1964-1967)"
    },
    {
        "Style":"Abstract-Expressionism",
        "Artwork":"Apparuerunt illis dispertitae linguae (Acts 1:14)",
        "Artist":"Salvador Dali",
        "Date":"1964-1967",
        "Link":"https:\/\/uploads0.wikiart.org\/images\/salvador-dali\/apparuerunt-illis-dispertitae-linguae-acts-1-14-1967.jpg",
        "hash":"787825096980cd3d7adab675c9967998",
        "category":"paint",
        "caption":"Apparuerunt illis dispertitae linguae (Acts 1:14) by Salvador Dali, Abstract-Expressionism (1964-1967)"
    },
    {
        "Style":"Abstract-Expressionism",
        "Artwork":"Jesus carrying the cross",
        "Artist":"Salvador Dali",
        "Date":"1964-1967",
        "Link":"https:\/\/uploads4.wikiart.org\/images\/salvador-dali\/jesus-carrying-the-cross-1967.jpg",
        "hash":"e186c3ab381d312261deb8839c8a9f36",
        "category":"paint",
        "caption":"Jesus carrying the cross by Salvador Dali, Abstract-Expressionism (1964-1967)"
    },
    {
        "Style":"Abstract-Expressionism",
        "Artwork":"Sponsabo te mihi in sempiternum (Song of Songs 2:12)",
        "Artist":"Salvador Dali",
        "Date":"1964-1967",
        "Link":"https:\/\/uploads3.wikiart.org\/images\/salvador-dali\/sponsabo-te-mihi-in-sempiternum-song-of-songs-2-12-1967.jpg",
        "hash":"a7078c2a4ef3d5a4f9caa8b24d988341",
        "category":"paint",
        "caption":"Sponsabo te mihi in sempiternum (Song of Songs 2:12) by Salvador Dali, Abstract-Expressionism (1964-1967)"
    },
    {
        "Style":"Abstract-Expressionism",
        "Artwork":"The Pool of Tears",
        "Artist":"Salvador Dali",
        "Date":"1969",
        "Link":"https:\/\/uploads1.wikiart.org\/images\/salvador-dali\/the-pool-of-tears.jpg",
        "hash":"b0086d0b41534a9c8aaa9fbd48afc1de",
        "category":"paint",
        "caption":"The Pool of Tears by Salvador Dali, Abstract-Expressionism (1969)"
    },
    {
        "Style":"Abstract-Expressionism",
        "Artwork":"Ipse erat Elias (Mark 1:4)",
        "Artist":"Salvador Dali",
        "Date":"1964-1967",
        "Link":"https:\/\/uploads4.wikiart.org\/images\/salvador-dali\/ipse-erat-elias-mark-1-4-1967.jpg",
        "hash":"79ac473d7e59d77fdd1e96324a0625e8",
        "category":"paint",
        "caption":"Ipse erat Elias (Mark 1:4) by Salvador Dali, Abstract-Expressionism (1964-1967)"
    },
    {
        "Style":"Abstract-Expressionism",
        "Artwork":"In principiodeus creavit...",
        "Artist":"Salvador Dali",
        "Date":"1964",
        "Link":"https:\/\/uploads4.wikiart.org\/images\/salvador-dali\/in-principiodeus-creavit-1964.jpg",
        "hash":"5d59af35af2cd2fd027dd60a037f1443",
        "category":"paint",
        "caption":"In principiodeus creavit... by Salvador Dali, Abstract-Expressionism (1964)"
    },
    {
        "Style":"Abstract-Expressionism",
        "Artwork":"Planctus David in mortem Saul",
        "Artist":"Salvador Dali",
        "Date":"1964-1967",
        "Link":"https:\/\/uploads0.wikiart.org\/images\/salvador-dali\/planctus-david-in-mortem-saul-1967.jpg",
        "hash":"950a4bb9bab54e0496bb76a1ab66895a",
        "category":"paint",
        "caption":"Planctus David in mortem Saul by Salvador Dali, Abstract-Expressionism (1964-1967)"
    },
    {
        "Style":"Abstract-Expressionism",
        "Artwork":"Homage to Meirronier",
        "Artist":"Salvador Dali",
        "Date":"1965",
        "Link":"https:\/\/uploads4.wikiart.org\/images\/salvador-dali\/homage-to-meirronier.jpg",
        "hash":"bf72453e3ce3365c0316c9159153e2cf",
        "category":"paint",
        "caption":"Homage to Meirronier by Salvador Dali, Abstract-Expressionism (1965)"
    },
    {
        "Style":"Abstract-Expressionism",
        "Artwork":"Arabs",
        "Artist":"Salvador Dali",
        "Date":"1980",
        "Link":"https:\/\/uploads0.wikiart.org\/images\/salvador-dali\/arabs-1.jpg",
        "hash":"76e158b95a42342ecf98c3cd858baa8f",
        "category":"paint",
        "caption":"Arabs by Salvador Dali, Abstract-Expressionism (1980)"
    },
    {
        "Style":"Abstract-Expressionism",
        "Artwork":"Plange, virgo, accincta. Sacco.",
        "Artist":"Salvador Dali",
        "Date":"1964-1967",
        "Link":"https:\/\/uploads7.wikiart.org\/images\/salvador-dali\/plange-virgo-accincta-sacco-1967.jpg",
        "hash":"1f26b2b3558cddf8527df3d8c07b3c6d",
        "category":"paint",
        "caption":"Plange, virgo, accincta. Sacco. by Salvador Dali, Abstract-Expressionism (1964-1967)"
    },
    {
        "Style":"Abstract-Expressionism",
        "Artwork":"Lazarus, come forth - Lazare, veni foras (John 11:44)",
        "Artist":"Salvador Dali",
        "Date":"1964",
        "Link":"https:\/\/uploads7.wikiart.org\/images\/salvador-dali\/lazarus-come-forth-lazare-veni-foras-1964.jpg",
        "hash":"97041d7c3ef47e3ab515b2cb6541a643",
        "category":"paint",
        "caption":"Lazarus, come forth - Lazare, veni foras (John 11:44) by Salvador Dali, Abstract-Expressionism (1964)"
    },
    {
        "Style":"Abstract-Expressionism",
        "Artwork":"Ecce quasi filius hominis in nubibus us caeli (Ezekiel 1:4)",
        "Artist":"Salvador Dali",
        "Date":"1964-1967",
        "Link":"https:\/\/uploads1.wikiart.org\/images\/salvador-dali\/ecce-quasi-filius-hominis-in-nubibus-us-caeli-ezekiel-1-4-1967.jpg",
        "hash":"c2ebb1a72139bcb98c33759a7d22ea13",
        "category":"paint",
        "caption":"Ecce quasi filius hominis in nubibus us caeli (Ezekiel 1:4) by Salvador Dali, Abstract-Expressionism (1964-1967)"
    },
    {
        "Style":"Abstract-Expressionism",
        "Artwork":"Iesus a Satana tentatur (Mark 1:13)",
        "Artist":"Salvador Dali",
        "Date":"1964",
        "Link":"https:\/\/uploads4.wikiart.org\/images\/salvador-dali\/iesus-a-satana-tentatur-mark-1-13-1964.jpg",
        "hash":"39ba0d157b8cbe4c08a5eaf5b02ae89a",
        "category":"paint",
        "caption":"Iesus a Satana tentatur (Mark 1:13) by Salvador Dali, Abstract-Expressionism (1964)"
    },
    {
        "Style":"Abstract-Expressionism",
        "Artwork":"Rubus incombustus (Exodus 3:2)",
        "Artist":"Salvador Dali",
        "Date":"1964-1967",
        "Link":"https:\/\/uploads8.wikiart.org\/images\/salvador-dali\/rubus-incombustus-exodus-3-2-1967.jpg",
        "hash":"6fcebcb6abffb8f40840372a75842fcf",
        "category":"paint",
        "caption":"Rubus incombustus (Exodus 3:2) by Salvador Dali, Abstract-Expressionism (1964-1967)"
    },
    {
        "Style":"Abstract-Expressionism",
        "Artwork":"Dali's Moustache",
        "Artist":"Salvador Dali",
        "Date":"1950",
        "Link":"https:\/\/uploads0.wikiart.org\/images\/salvador-dali\/dali-s-moustache.jpg",
        "hash":"9f1ad0e54cb35e32c9d2072038908746",
        "category":"paint",
        "caption":"Dali's Moustache by Salvador Dali, Abstract-Expressionism (1950)"
    },
    {
        "Style":"Abstract-Expressionism",
        "Artwork":"Proelium magnum in caelo",
        "Artist":"Salvador Dali",
        "Date":"1964-1967",
        "Link":"https:\/\/uploads4.wikiart.org\/images\/salvador-dali\/proelium-magnum-in-caelo-1967.jpg",
        "hash":"c14c40882ac0cd2cd4fb59136fdc5ece",
        "category":"paint",
        "caption":"Proelium magnum in caelo by Salvador Dali, Abstract-Expressionism (1964-1967)"
    },
    {
        "Style":"Abstract-Expressionism",
        "Artwork":"Et posuerunt eum in monumento (Mark 15:46)",
        "Artist":"Salvador Dali",
        "Date":"1964",
        "Link":"https:\/\/uploads2.wikiart.org\/images\/salvador-dali\/et-posuerunt-eum-in-monumento-mark-15-46-1964.jpg",
        "hash":"d3f1b01f376ec2a554803679d832cbba",
        "category":"paint",
        "caption":"Et posuerunt eum in monumento (Mark 15:46) by Salvador Dali, Abstract-Expressionism (1964)"
    },
    {
        "Style":"Abstract-Expressionism",
        "Artwork":"Emissa voce magna expiravit (Mark 15:37)",
        "Artist":"Salvador Dali",
        "Date":"1964-1967",
        "Link":"https:\/\/uploads0.wikiart.org\/images\/salvador-dali\/emissa-voce-magna-expiravit-mark-15-37-1967.jpg",
        "hash":"717c24f64558a689beaac186eedb695d",
        "category":"paint",
        "caption":"Emissa voce magna expiravit (Mark 15:37) by Salvador Dali, Abstract-Expressionism (1964-1967)"
    },
    {
        "Style":"Abstract-Expressionism",
        "Artwork":"Aquae diluvii super terram (Genesis 6:17)",
        "Artist":"Salvador Dali",
        "Date":"1964-1967",
        "Link":"https:\/\/uploads1.wikiart.org\/images\/salvador-dali\/aquae-diluvii-super-terram-genesis-6-17-1967.jpg",
        "hash":"3cf97c08211f4fec1e6f6553b1bd4c10",
        "category":"paint",
        "caption":"Aquae diluvii super terram (Genesis 6:17) by Salvador Dali, Abstract-Expressionism (1964-1967)"
    },
    {
        "Style":"Abstract-Expressionism",
        "Artwork":"Mulier amicta sole",
        "Artist":"Salvador Dali",
        "Date":"1964-1967",
        "Link":"https:\/\/uploads7.wikiart.org\/images\/salvador-dali\/mulier-amicta-sole-1967.jpg",
        "hash":"a0af05a1bcdb20e1ec9fc44007e9ffd1",
        "category":"paint",
        "caption":"Mulier amicta sole by Salvador Dali, Abstract-Expressionism (1964-1967)"
    },
    {
        "Style":"Abstract-Expressionism",
        "Artwork":"The Infanta (Standing Woman)",
        "Artist":"Salvador Dali",
        "Date":"1961",
        "Link":"https:\/\/uploads1.wikiart.org\/images\/salvador-dali\/the-infanta-standing-woman.jpg",
        "hash":"16bc153887a9d155dd8c28f24c177870",
        "category":"paint",
        "caption":"The Infanta (Standing Woman) by Salvador Dali, Abstract-Expressionism (1961)"
    },
    {
        "Style":"Abstract-Expressionism",
        "Artwork":"Iesus flagellatus (John 19:1)",
        "Artist":"Salvador Dali",
        "Date":"1964",
        "Link":"https:\/\/uploads7.wikiart.org\/images\/salvador-dali\/iesus-flagellatus-john-19-1-1964.jpg",
        "hash":"168b67d8ab58424a2c6e4ff6e12ee1a7",
        "category":"paint",
        "caption":"Iesus flagellatus (John 19:1) by Salvador Dali, Abstract-Expressionism (1964)"
    },
    {
        "Style":"Abstract-Expressionism",
        "Artwork":"Arabs - the Death of Raymond Lulle",
        "Artist":"Salvador Dali",
        "Date":"1963",
        "Link":"https:\/\/uploads7.wikiart.org\/images\/salvador-dali\/arabs-the-death-of-raymond-lulle.jpg",
        "hash":"158ec23c528c73597fbf8f7de762a33a",
        "category":"paint",
        "caption":"Arabs - the Death of Raymond Lulle by Salvador Dali, Abstract-Expressionism (1963)"
    },
    {
        "Style":"Abstract-Expressionism",
        "Artwork":"Arabs - the Death of Raimundus Lullus",
        "Artist":"Salvador Dali",
        "Date":"1963",
        "Link":"https:\/\/uploads1.wikiart.org\/images\/salvador-dali\/arabs-the-death-of-raimundus-lullus.jpg",
        "hash":"ab364d8928ca8389a2588ed2b772b803",
        "category":"paint",
        "caption":"Arabs - the Death of Raimundus Lullus by Salvador Dali, Abstract-Expressionism (1963)"
    },
    {
        "Style":"Abstract-Expressionism",
        "Artwork":"Arab",
        "Artist":"Salvador Dali",
        "Date":"1962",
        "Link":"https:\/\/uploads6.wikiart.org\/images\/salvador-dali\/arab.jpg",
        "hash":"3b5214a81f6179ea9e949cc529a7c28d",
        "category":"paint",
        "caption":"Arab by Salvador Dali, Abstract-Expressionism (1962)"
    },
    {
        "Style":"Abstract-Expressionism",
        "Artwork":"The Christian Knight (Dali's Horses)",
        "Artist":"Salvador Dali",
        "Date":"1971",
        "Link":"https:\/\/uploads0.wikiart.org\/images\/salvador-dali\/the-christian-knight-dali-s-horses.jpg",
        "hash":"bb2284f7a3929bbc265e71bf6a88dcb0",
        "category":"paint",
        "caption":"The Christian Knight (Dali's Horses) by Salvador Dali, Abstract-Expressionism (1971)"
    },
    {
        "Style":"Abstract-Expressionism",
        "Artwork":"Study for Deoxyribonucleic Acid Arabs",
        "Artist":"Salvador Dali",
        "Date":"1963",
        "Link":"https:\/\/uploads5.wikiart.org\/images\/salvador-dali\/study-for-deoxyribonucleic-acid-arabs-1.jpg",
        "hash":"3a7ad8100c246ec6dd09402bb7e72793",
        "category":"paint",
        "caption":"Study for Deoxyribonucleic Acid Arabs by Salvador Dali, Abstract-Expressionism (1963)"
    },
    {
        "Style":"Abstract-Expressionism",
        "Artwork":"Nativity",
        "Artist":"Salvador Dali",
        "Date":"1959",
        "Link":"https:\/\/uploads8.wikiart.org\/00164\/images\/salvador-dali\/nativity-1959.jpg",
        "hash":"f540ea9290f9cd7b9977f8f3b46b1494",
        "category":"paint",
        "caption":"Nativity by Salvador Dali, Abstract-Expressionism (1959)"
    },
    {
        "Style":"Abstract-Expressionism",
        "Artwork":"Tertia die resurrexit",
        "Artist":"Salvador Dali",
        "Date":"1964-1967",
        "Link":"https:\/\/uploads1.wikiart.org\/images\/salvador-dali\/tertia-die-resurrexit-1967.jpg",
        "hash":"4c5a2c0fda89521cf7bab9192f4d4c07",
        "category":"paint",
        "caption":"Tertia die resurrexit by Salvador Dali, Abstract-Expressionism (1964-1967)"
    },
    {
        "Style":"Abstract-Expressionism",
        "Artwork":"Tolle, tolle, crucifige eum (John 19:15)",
        "Artist":"Salvador Dali",
        "Date":"1964-1967",
        "Link":"https:\/\/uploads7.wikiart.org\/images\/salvador-dali\/tolle-tolle-crucifige-eum-john-19-15-1967.jpg",
        "hash":"bff16e692e2764db361c96d9b7dc2f57",
        "category":"paint",
        "caption":"Tolle, tolle, crucifige eum (John 19:15) by Salvador Dali, Abstract-Expressionism (1964-1967)"
    },
    {
        "Style":"Abstract-Expressionism",
        "Artwork":"Raphaelesque Hallucination",
        "Artist":"Salvador Dali",
        "Date":"1979",
        "Link":"https:\/\/uploads1.wikiart.org\/images\/salvador-dali\/raphaelesque-hallucination.jpg",
        "hash":"5eff4fc3c106b78552605a16b0131856",
        "category":"paint",
        "caption":"Raphaelesque Hallucination by Salvador Dali, Abstract-Expressionism (1979)"
    },
    {
        "Style":"Abstract-Expressionism",
        "Artwork":"Canita tuba in Sion (Joel 2:1)",
        "Artist":"Salvador Dali",
        "Date":"1964-1967",
        "Link":"https:\/\/uploads8.wikiart.org\/images\/salvador-dali\/canita-tuba-in-sion-joel-2-1-1967.jpg",
        "hash":"3597db1fb277b54a65d4e5134ced86aa",
        "category":"paint",
        "caption":"Canita tuba in Sion (Joel 2:1) by Salvador Dali, Abstract-Expressionism (1964-1967)"
    },
    {
        "Style":"Abstract-Expressionism",
        "Artwork":"Arabs",
        "Artist":"Salvador Dali",
        "Date":"1980",
        "Link":"https:\/\/uploads7.wikiart.org\/images\/salvador-dali\/arabs.jpg",
        "hash":"e1b01bb234d53a707f9896ad14d8f2d7",
        "category":"paint",
        "caption":"Arabs by Salvador Dali, Abstract-Expressionism (1980)"
    },
    {
        "Style":"Abstract-Expressionism",
        "Artwork":"Extravaganza",
        "Artist":"Salvador Dali",
        "Date":"1959",
        "Link":"https:\/\/uploads3.wikiart.org\/00164\/images\/salvador-dali\/extravaganza-1959.jpg",
        "hash":"9ba5bc1f9f7e6f53e0418dbb053438b8",
        "category":"paint",
        "caption":"Extravaganza by Salvador Dali, Abstract-Expressionism (1959)"
    },
    {
        "Style":"Abstract-Expressionism",
        "Artwork":"Abraham, Abraham! (Genesis 22:2)",
        "Artist":"Salvador Dali",
        "Date":"1964-1967",
        "Link":"https:\/\/uploads8.wikiart.org\/images\/salvador-dali\/abraham-abraham-genesis-22-2-1967.jpg",
        "hash":"a86b9defc504753d2eea5608c3a8e27f",
        "category":"paint",
        "caption":"Abraham, Abraham! (Genesis 22:2) by Salvador Dali, Abstract-Expressionism (1964-1967)"
    },
    {
        "Style":"Abstract-Expressionism",
        "Artwork":"Rhinocerotic Portrait of Vermeer's 'Lacemaker'",
        "Artist":"Salvador Dali",
        "Date":"1955",
        "Link":"https:\/\/uploads1.wikiart.org\/images\/salvador-dali\/rhinocerotic-portrait-of-vermeer-s-lacemaker.jpg",
        "hash":"966a5699887dff2540132d050f4f9a1b",
        "category":"paint",
        "caption":"Rhinocerotic Portrait of Vermeer's 'Lacemaker' by Salvador Dali, Abstract-Expressionism (1955)"
    },
    {
        "Style":"Abstract-Expressionism",
        "Artwork":"Angel",
        "Artist":"Salvador Dali",
        "Date":"1958",
        "Link":"https:\/\/uploads7.wikiart.org\/images\/salvador-dali\/angel.jpg",
        "hash":"b88b47fa1268003e73b8d435383db5b1",
        "category":"paint",
        "caption":"Angel by Salvador Dali, Abstract-Expressionism (1958)"
    },
    {
        "Style":"Abstract-Expressionism",
        "Artwork":"Et baptizatus est a Ioanne in Iordane (Luke 3:3)",
        "Artist":"Salvador Dali",
        "Date":"1964",
        "Link":"https:\/\/uploads3.wikiart.org\/images\/salvador-dali\/et-baptizatus-est-a-ioanne-in-iordane-luke-3-3.jpg",
        "hash":"26700ebefe506a5d5dd724010d6964eb",
        "category":"paint",
        "caption":"Et baptizatus est a Ioanne in Iordane (Luke 3:3) by Salvador Dali, Abstract-Expressionism (1964)"
    },
    {
        "Style":"Abstract-Expressionism",
        "Artwork":"Group Surrounding a Reclining Nude - Velazquez",
        "Artist":"Salvador Dali",
        "Date":"1980-1981",
        "Link":"https:\/\/uploads6.wikiart.org\/images\/salvador-dali\/group-surrounding-a-reclining-nude-velazquez-1981.jpg",
        "hash":"8baf2eced7e9aa0ce8ba1620d7dd397e",
        "category":"paint",
        "caption":"Group Surrounding a Reclining Nude - Velazquez by Salvador Dali, Abstract-Expressionism (1980-1981)"
    },
    {
        "Style":"Abstract-Expressionism",
        "Artwork":"Noe qui primus plantavit vineam\u2026 (Genesis 9:20f)",
        "Artist":"Salvador Dali",
        "Date":"1964-1967",
        "Link":"https:\/\/uploads7.wikiart.org\/images\/salvador-dali\/noe-qui-primus-plantavit-vineam-genesis-9-20f-1967.jpg",
        "hash":"521e2706b282d75184965f8736cc6611",
        "category":"paint",
        "caption":"Noe qui primus plantavit vineam\u2026 (Genesis 9:20f) by Salvador Dali, Abstract-Expressionism (1964-1967)"
    },
    {
        "Style":"Abstract-Expressionism",
        "Artwork":"Ex Aegypto vocavi filium meum",
        "Artist":"Salvador Dali",
        "Date":"1964",
        "Link":"https:\/\/uploads0.wikiart.org\/images\/salvador-dali\/ex-aegypto-vocavi-filium-meum-1964.jpg",
        "hash":"e4295b48bba2f735ee1235b3750fb760",
        "category":"paint",
        "caption":"Ex Aegypto vocavi filium meum by Salvador Dali, Abstract-Expressionism (1964)"
    },
    {
        "Style":"Abstract-Expressionism",
        "Artwork":"Vanitas vanitatum (Ecclesiastes 1:12f)",
        "Artist":"Salvador Dali",
        "Date":"1964",
        "Link":"https:\/\/uploads0.wikiart.org\/images\/salvador-dali\/ecclesiastes-preacher-of-surprising-joy-1-4.jpg",
        "hash":"b5483f0bdc63169bb1ab8b2531ca4100",
        "category":"paint",
        "caption":"Vanitas vanitatum (Ecclesiastes 1:12f) by Salvador Dali, Abstract-Expressionism (1964)"
    },
    {
        "Style":"Abstract-Expressionism",
        "Artwork":"Seduxisti me, Domine",
        "Artist":"Salvador Dali",
        "Date":"1964-1967",
        "Link":"https:\/\/uploads8.wikiart.org\/images\/salvador-dali\/seduxisti-me-domine-1967.jpg",
        "hash":"ec50e51a4d582c0424728b3d981e75bc",
        "category":"paint",
        "caption":"Seduxisti me, Domine by Salvador Dali, Abstract-Expressionism (1964-1967)"
    },
    {
        "Style":"Abstract-Expressionism",
        "Artwork":"Caligula's Horse (Dali's Horses)",
        "Artist":"Salvador Dali",
        "Date":"1971",
        "Link":"https:\/\/uploads5.wikiart.org\/images\/salvador-dali\/caligula-s-horse-dali-s-horses.jpg",
        "hash":"54e41f2a6ff1b0c4a129ed284290daa3",
        "category":"paint",
        "caption":"Caligula's Horse (Dali's Horses) by Salvador Dali, Abstract-Expressionism (1971)"
    },
    {
        "Style":"Abstract-Expressionism",
        "Artwork":"Angelus excussit flammamignis (Daniel 3:23)",
        "Artist":"Salvador Dali",
        "Date":"1964-1967",
        "Link":"https:\/\/uploads3.wikiart.org\/images\/salvador-dali\/angelus-excussit-flammamignis-daniel-3-23-1967.jpg",
        "hash":"8230e0fe4b8a749eea5386dd4bc8b4f7",
        "category":"paint",
        "caption":"Angelus excussit flammamignis (Daniel 3:23) by Salvador Dali, Abstract-Expressionism (1964-1967)"
    },
    {
        "Style":"Abstract-Expressionism",
        "Artwork":"Iesus super mare ambulans (Matthew 14:26)",
        "Artist":"Salvador Dali",
        "Date":"1964",
        "Link":"https:\/\/uploads1.wikiart.org\/images\/salvador-dali\/iesus-super-mare-ambulans-matthew-14-26-1964.jpg",
        "hash":"4eb272ce6370eec8b9d0d5b8733315a8",
        "category":"paint",
        "caption":"Iesus super mare ambulans (Matthew 14:26) by Salvador Dali, Abstract-Expressionism (1964)"
    },
    {
        "Style":"Abstract-Expressionism",
        "Artwork":"Spiritus promptus est, caro vero infirma",
        "Artist":"Salvador Dali",
        "Date":"1964-1967",
        "Link":"https:\/\/uploads1.wikiart.org\/images\/salvador-dali\/spiritus-promptus-est-caro-vero-infirma-1967.jpg",
        "hash":"de0b8681b860898b5db87786db941193",
        "category":"paint",
        "caption":"Spiritus promptus est, caro vero infirma by Salvador Dali, Abstract-Expressionism (1964-1967)"
    },
    {
        "Style":"Abstract-Expressionism",
        "Artwork":"Angel of Light",
        "Artist":"Salvador Dali",
        "Date":"1960",
        "Link":"https:\/\/uploads7.wikiart.org\/images\/salvador-dali\/angel-of-light.jpg",
        "hash":"c97561f64e8d506f2fc68d9e4da12301",
        "category":"paint",
        "caption":"Angel of Light by Salvador Dali, Abstract-Expressionism (1960)"
    },
    {
        "Style":"Abstract-Expressionism",
        "Artwork":"Cadaver in seoulchro Elisei (2 Kings 13:21)",
        "Artist":"Salvador Dali",
        "Date":"1964-1967",
        "Link":"https:\/\/uploads3.wikiart.org\/images\/salvador-dali\/cadaver-in-seoulchro-elisei-2-kings-13-21-1967.jpg",
        "hash":"883b8e8b829d06847c6a571fe034bf53",
        "category":"paint",
        "caption":"Cadaver in seoulchro Elisei (2 Kings 13:21) by Salvador Dali, Abstract-Expressionism (1964-1967)"
    },
    {
        "Style":"Abstract-Expressionism",
        "Artwork":"Leda's Swan (Leda and the Swan)",
        "Artist":"Salvador Dali",
        "Date":"1961",
        "Link":"https:\/\/uploads4.wikiart.org\/images\/salvador-dali\/leda-s-swan-leda-and-the-swan.jpg",
        "hash":"ff8b039287e13ba8f47629cc62e47cb8",
        "category":"paint",
        "caption":"Leda's Swan (Leda and the Swan) by Salvador Dali, Abstract-Expressionism (1961)"
    },
    {
        "Style":"Abstract-Expressionism",
        "Artwork":"Filiae Herodiadis saltatio (Matthew 14:6)",
        "Artist":"Salvador Dali",
        "Date":"1964",
        "Link":"https:\/\/uploads1.wikiart.org\/images\/salvador-dali\/filiae-herodiadis-saltatio-matthew-14-6-1964.jpg",
        "hash":"007afbb8ff5a7475863e60e2c7ea9e28",
        "category":"paint",
        "caption":"Filiae Herodiadis saltatio (Matthew 14:6) by Salvador Dali, Abstract-Expressionism (1964)"
    },
    {
        "Style":"Abstract-Expressionism",
        "Artwork":"Christ. From 'The Apocalypse of St. John'",
        "Artist":"Salvador Dali",
        "Date":"1958",
        "Link":"https:\/\/uploads3.wikiart.org\/images\/salvador-dali\/christ-from-the-apocalypse-of-st-john.jpg",
        "hash":"87643b03f39669c86c0fcb0ab56dc4be",
        "category":"paint",
        "caption":"Christ. From 'The Apocalypse of St. John' by Salvador Dali, Abstract-Expressionism (1958)"
    },
    {
        "Style":"Abstract-Expressionism",
        "Artwork":"Ego sum Dominus Deus tuus... (Exodus 34:28)",
        "Artist":"Salvador Dali",
        "Date":"1964-1967",
        "Link":"https:\/\/uploads0.wikiart.org\/images\/salvador-dali\/ego-sum-dominus-deus-tuus-exodus-34-28-1967.jpg",
        "hash":"ecf28b21f55167d94aadd3b9d8255273",
        "category":"paint",
        "caption":"Ego sum Dominus Deus tuus... (Exodus 34:28) by Salvador Dali, Abstract-Expressionism (1964-1967)"
    },
    {
        "Style":"Abstract-Expressionism",
        "Artwork":"Leviathan (Job 40:21)",
        "Artist":"Salvador Dali",
        "Date":"1964-1967",
        "Link":"https:\/\/uploads8.wikiart.org\/images\/salvador-dali\/leviathan-job-40-21-1967.jpg",
        "hash":"edc61e0d5f809abf3102045cf10e41b8",
        "category":"paint",
        "caption":"Leviathan (Job 40:21) by Salvador Dali, Abstract-Expressionism (1964-1967)"
    },
    {
        "Style":"Abstract-Expressionism",
        "Artwork":"Study for 'Christ of St. John of the Cross'",
        "Artist":"Salvador Dali",
        "Date":"1950-1951",
        "Link":"https:\/\/uploads2.wikiart.org\/images\/salvador-dali\/study-for-christ-of-st-john-of-the-cross-1951.jpg",
        "hash":"8524c7dbf563481402febc8d872f43b8",
        "category":"paint",
        "caption":"Study for 'Christ of St. John of the Cross' by Salvador Dali, Abstract-Expressionism (1950-1951)"
    },
    {
        "Style":"Abstract-Expressionism",
        "Artwork":"Night in the Hotel (Abstract in Black and White)",
        "Artist":"Salvador Dali",
        "Date":"1965",
        "Link":"https:\/\/uploads3.wikiart.org\/images\/salvador-dali\/night-in-the-hotel-abstract-in-black-and-white.jpg",
        "hash":"8287abc291363179e13c5cb57b988176",
        "category":"paint",
        "caption":"Night in the Hotel (Abstract in Black and White) by Salvador Dali, Abstract-Expressionism (1965)"
    },
    {
        "Style":"Abstract-Expressionism",
        "Artwork":"Iesu transfigurato (Mark 9:4f)",
        "Artist":"Salvador Dali",
        "Date":"1964",
        "Link":"https:\/\/uploads8.wikiart.org\/images\/salvador-dali\/iesu-transfigurato-mark-9-4f-1964.jpg",
        "hash":"b44b6bc5b4f707cb4e80ed77a90ac185",
        "category":"paint",
        "caption":"Iesu transfigurato (Mark 9:4f) by Salvador Dali, Abstract-Expressionism (1964)"
    },
    {
        "Style":"Abstract-Expressionism",
        "Artwork":"Vir et mulier in Paradiso Voluptatis",
        "Artist":"Salvador Dali",
        "Date":"1964-1967",
        "Link":"https:\/\/uploads7.wikiart.org\/images\/salvador-dali\/vir-et-mulier-in-paradiso-voluptatis-1967.jpg",
        "hash":"a69d4e0e71f7cc97c4357b49256df655",
        "category":"paint",
        "caption":"Vir et mulier in Paradiso Voluptatis by Salvador Dali, Abstract-Expressionism (1964-1967)"
    },
    {
        "Style":"Abstract-Expressionism",
        "Artwork":"Religious Scene in Particles",
        "Artist":"Salvador Dali",
        "Date":"1958",
        "Link":"https:\/\/uploads3.wikiart.org\/images\/salvador-dali\/religious-scene-in-particles.jpg",
        "hash":"24d41348e260cbd641da378c8bab4dac",
        "category":"paint",
        "caption":"Religious Scene in Particles by Salvador Dali, Abstract-Expressionism (1958)"
    },
    {
        "Style":"Abstract-Expressionism",
        "Artwork":"Oblatio munda",
        "Artist":"Salvador Dali",
        "Date":"1964-1967",
        "Link":"https:\/\/uploads2.wikiart.org\/images\/salvador-dali\/oblatio-munda-1967.jpg",
        "hash":"5ca51c5bf1b43aa2751b30a8182ec2fa",
        "category":"paint",
        "caption":"Oblatio munda by Salvador Dali, Abstract-Expressionism (1964-1967)"
    },
    {
        "Style":"Abstract-Expressionism",
        "Artwork":"Elias per turbinem super currus igneus",
        "Artist":"Salvador Dali",
        "Date":"1964-1967",
        "Link":"https:\/\/uploads0.wikiart.org\/images\/salvador-dali\/elias-per-turbinem-super-currus-igneus-1967.jpg",
        "hash":"624b4cfd5a4ca1c0bca1afc51faaf2d3",
        "category":"paint",
        "caption":"Elias per turbinem super currus igneus by Salvador Dali, Abstract-Expressionism (1964-1967)"
    },
    {
        "Style":"Abstract-Expressionism",
        "Artwork":"Self-Portrait (Photomontage with the famous 'Mao-Marilyn' that Philippe Halsman created at Dali's wish)",
        "Artist":"Salvador Dali",
        "Date":"1972",
        "Link":"https:\/\/uploads6.wikiart.org\/images\/salvador-dali\/self-portrait-photomontage-with-the-famous-mao-marilyn-that-philippe-halsman-created-at-dali-s.jpg",
        "hash":"b1fe507eef03547d83403e5509cac4be",
        "category":"paint",
        "caption":"Self-Portrait (Photomontage with the famous 'Mao-Marilyn' that Philippe Halsman created at Dali's wish) by Salvador Dali, Abstract-Expressionism (1972)"
    },
    {
        "Style":"Abstract-Expressionism",
        "Artwork":"Ecce virgo concipiet (Isaiah 7:14)",
        "Artist":"Salvador Dali",
        "Date":"1964-1967",
        "Link":"https:\/\/uploads3.wikiart.org\/images\/salvador-dali\/ecce-virgo-concipiet-isaiah-7-14-1967.jpg",
        "hash":"34ffe74de275dfe3c4ee5506dc209aa3",
        "category":"paint",
        "caption":"Ecce virgo concipiet (Isaiah 7:14) by Salvador Dali, Abstract-Expressionism (1964-1967)"
    },
    {
        "Style":"Abstract-Expressionism",
        "Artwork":"Vinea electa (Isaiah 5:6)",
        "Artist":"Salvador Dali",
        "Date":"1964-1967",
        "Link":"https:\/\/uploads3.wikiart.org\/images\/salvador-dali\/vinea-electa-isaiah-5-6-1967.jpg",
        "hash":"fe2d47c698b599c1cae2ff548f5ca481",
        "category":"paint",
        "caption":"Vinea electa (Isaiah 5:6) by Salvador Dali, Abstract-Expressionism (1964-1967)"
    },
    {
        "Style":"Abstract-Expressionism",
        "Artwork":"Ecce homo",
        "Artist":"Salvador Dali",
        "Date":"1964-1967",
        "Link":"https:\/\/uploads7.wikiart.org\/images\/salvador-dali\/ecce-homo-1967.jpg",
        "hash":"21db6fddeab4cadda50dbbdd089fc01a",
        "category":"paint",
        "caption":"Ecce homo by Salvador Dali, Abstract-Expressionism (1964-1967)"
    },
    {
        "Style":"Abstract-Expressionism",
        "Artwork":"Cherub super limen domus (Ezekiel 9:3)",
        "Artist":"Salvador Dali",
        "Date":"1964-1967",
        "Link":"https:\/\/uploads7.wikiart.org\/images\/salvador-dali\/cherub-super-limen-domus-ezekiel-9-3-1967.jpg",
        "hash":"5b5ec1cbd595c5c0c2a4c59f162d4f0c",
        "category":"paint",
        "caption":"Cherub super limen domus (Ezekiel 9:3) by Salvador Dali, Abstract-Expressionism (1964-1967)"
    },
    {
        "Style":"Abstract-Expressionism",
        "Artwork":"Veni, Domine Jesu (Revelation 22:17)",
        "Artist":"Salvador Dali",
        "Date":"1964-1967",
        "Link":"https:\/\/uploads4.wikiart.org\/images\/salvador-dali\/veni-domine-jesu-revelation-22-17-1967.jpg",
        "hash":"30e26ff46ce1be19ec4249444ef94f7e",
        "category":"paint",
        "caption":"Veni, Domine Jesu (Revelation 22:17) by Salvador Dali, Abstract-Expressionism (1964-1967)"
    },
    {
        "Style":"Abstract-Expressionism",
        "Artwork":"Gloria vultus Moysi (Exodus 34:29)",
        "Artist":"Salvador Dali",
        "Date":"1964",
        "Link":"https:\/\/uploads3.wikiart.org\/images\/salvador-dali\/gloria-vultus-moysi-exodus-34-29-1964.jpg",
        "hash":"50a85d2cdbaff099a6251ab648a54584",
        "category":"paint",
        "caption":"Gloria vultus Moysi (Exodus 34:29) by Salvador Dali, Abstract-Expressionism (1964)"
    },
    {
        "Style":"Abstract-Expressionism",
        "Artwork":"Vox clamantis",
        "Artist":"Salvador Dali",
        "Date":"1964-1967",
        "Link":"https:\/\/uploads2.wikiart.org\/images\/salvador-dali\/vox-clamantis-1967.jpg",
        "hash":"6f593b6f798e0531ca0558a49f6e5513",
        "category":"paint",
        "caption":"Vox clamantis by Salvador Dali, Abstract-Expressionism (1964-1967)"
    },
    {
        "Style":"Abstract-Expressionism",
        "Artwork":"Quis ascendet in mentem Domini?",
        "Artist":"Salvador Dali",
        "Date":"1964-1967",
        "Link":"https:\/\/uploads1.wikiart.org\/images\/salvador-dali\/quis-ascendet-in-mentem-domini-1967.jpg",
        "hash":"113cd6582f66ee49667eaca59d733530",
        "category":"paint",
        "caption":"Quis ascendet in mentem Domini? by Salvador Dali, Abstract-Expressionism (1964-1967)"
    },
    {
        "Style":"Abstract-Expressionism",
        "Artwork":"Rhinocerotic Figures",
        "Artist":"Salvador Dali",
        "Date":"1955",
        "Link":"https:\/\/uploads4.wikiart.org\/images\/salvador-dali\/rhinocerotic-figures.jpg",
        "hash":"7c83d2e28be22d0186f404fb54f0063c",
        "category":"paint",
        "caption":"Rhinocerotic Figures by Salvador Dali, Abstract-Expressionism (1955)"
    },
    {
        "Style":"Abstract-Expressionism",
        "Artwork":"The Dalinian Senyera (Catalonian National Flag)",
        "Artist":"Salvador Dali",
        "Date":"1970",
        "Link":"https:\/\/uploads2.wikiart.org\/images\/salvador-dali\/the-dalinian-senyera-catalonian-national-flag.jpg",
        "hash":"f0e61cb39ab535a293a0d2c7827ea747",
        "category":"paint",
        "caption":"The Dalinian Senyera (Catalonian National Flag) by Salvador Dali, Abstract-Expressionism (1970)"
    },
    {
        "Style":"Abstract-Expressionism",
        "Artwork":"Iosias sepultus in mausoleum patrum (2 Chronicles 35:24)",
        "Artist":"Salvador Dali",
        "Date":"1964-1967",
        "Link":"https:\/\/uploads7.wikiart.org\/images\/salvador-dali\/iosias-sepultus-in-mausoleum-patrum-2-chronicles-35-24-1967.jpg",
        "hash":"67fe7ee2009cba72d288489c59fd20d4",
        "category":"paint",
        "caption":"Iosias sepultus in mausoleum patrum (2 Chronicles 35:24) by Salvador Dali, Abstract-Expressionism (1964-1967)"
    },
    {
        "Style":"Abstract-Expressionism",
        "Artwork":"Mane, thecel, phares",
        "Artist":"Salvador Dali",
        "Date":"1964-1967",
        "Link":"https:\/\/uploads7.wikiart.org\/images\/salvador-dali\/mane-thecel-phares-1967.jpg",
        "hash":"8e76af36ef749d7d4dd562f0e3f93063",
        "category":"paint",
        "caption":"Mane, thecel, phares by Salvador Dali, Abstract-Expressionism (1964-1967)"
    },
    {
        "Style":"Abstract-Expressionism",
        "Artwork":"Nabuchodonsor rex Babylons",
        "Artist":"Salvador Dali",
        "Date":"1964-1967",
        "Link":"https:\/\/uploads6.wikiart.org\/images\/salvador-dali\/nabuchodonsor-rex-babylons-1967.jpg",
        "hash":"32755b09272e7e2bf360db92ec1f2827",
        "category":"paint",
        "caption":"Nabuchodonsor rex Babylons by Salvador Dali, Abstract-Expressionism (1964-1967)"
    }
]